url2epub.py
url2epub-1.0.6.dist-info/licenses/LICENSE
url2epub-1.0.6.dist-info/METADATA
url2epub-1.0.6.dist-info/WHEEL
url2epub-1.0.6.dist-info/entry_points.txt
url2epub-1.0.6.dist-info/top_level.txt
url2epub-1.0.6.dist-info/RECORD
