Metadata-Version: 2.4
Name: url2epub
Version: 1.0.6
Summary: A CLI program to convert an URL to an epub using Readability & Pandoc.
Author-email: berru <berru@riseup.net>
License-Expression: MIT
Project-URL: Homepage, https://git.sr.ht/~berru/url2epub
Keywords: epub,cli
Classifier: Programming Language :: Python :: 3
Classifier: Operating System :: OS Independent
Classifier: Development Status :: 5 - Production/Stable
Classifier: Topic :: Utilities
Requires-Python: >=3.9
License-File: LICENSE
Requires-Dist: readability-lxml
Requires-Dist: pandoc
Requires-Dist: requests
Requires-Dist: unidecode
Dynamic: license-file
